Metadata-Version: 2.1
Name: listas-anidadas
Version: 1.4.0
Summary: Module that prints nested list items line by line
Home-page: https://fortinux.com
Author: Fortinux
Author-email: info@fortinux.com
License-File: LICENSE
